emailrouter/__init__.py
emailrouter/email.py
emailrouter/filters.py
emailrouter/handlers.py
emailrouter/routing.py
emailrouter/testsuite.py
emailrouter/utils.py
emailrouter/tests/__init__.py
emailrouter/tests/test_filters.py
emailrouter/tests/test_router.py
email_router-1.0.3.dist-info/LICENSE
email_router-1.0.3.dist-info/METADATA
email_router-1.0.3.dist-info/WHEEL
email_router-1.0.3.dist-info/top_level.txt
email_router-1.0.3.dist-info/RECORD
