Metadata-Version: 2.1
Name: email-router
Version: 1.0.3
Summary: A straightforward and efficient inbound email router.
Home-page: https://github.com/Ninjaclasher/email-router
Author: Evan Zhang
Classifier: Development Status :: 5 - Production/Stable
Classifier: Environment :: Console
Classifier: Intended Audience :: Developers
Classifier: License :: OSI Approved :: GNU Affero General Public License v3 or later (AGPLv3+)
Classifier: Operating System :: OS Independent
Classifier: Programming Language :: Python
Classifier: Programming Language :: Python :: 3.9
Classifier: Programming Language :: Python :: 3.10
License-File: LICENSE
Requires-Dist: pyyaml
Requires-Dist: mail-parser
Requires-Dist: html2text
